{
  "id": "005-auth-split-login",
  "name": "Split Login (Brand Panel)",
  "kind": "component",
  "domain": [
    "forms"
  ],
  "tags": {
    "aesthetic": [
      "modern"
    ],
    "theme": "dark",
    "palette": [
      "蓝紫渐变"
    ],
    "patterns": [],
    "capabilities": [
      "responsive"
    ],
    "tokens": [
      "tailwind"
    ]
  },
  "source": {
    "url": "https://tailwindcss.com/plus/ui-blocks/application-ui/forms/sign-in-forms",
    "title": "Tailwind UI Blocks - Sign-in and Registration"
  }
}
